snake_cmd.py
ruben_snake_cmd-0.3.0.dist-info/LICENSE
ruben_snake_cmd-0.3.0.dist-info/METADATA
ruben_snake_cmd-0.3.0.dist-info/WHEEL
ruben_snake_cmd-0.3.0.dist-info/entry_points.txt
ruben_snake_cmd-0.3.0.dist-info/top_level.txt
ruben_snake_cmd-0.3.0.dist-info/RECORD
