Metadata-Version: 2.1
Name: ruben-snake-cmd
Version: 0.3.0
Summary: Command-line version of the classic Snake game.
Home-page: https://github.com/Ruben9922/snake-cmd
Author: Ruben Dougall
Author-email: info.ruebz999@gmail.com
Keywords: snake game console command-line curses
Classifier: Programming Language :: Python :: 3
Classifier: License :: OSI Approved :: GNU General Public License v3 (GPLv3)
Classifier: Operating System :: OS Independent
Classifier: Environment :: Console :: Curses
Classifier: Natural Language :: English
Classifier: Topic :: Games/Entertainment :: Arcade
Requires-Python: >=3.6
License-File: LICENSE
Requires-Dist: numpy
Requires-Dist: ruben-curses-game-utilities
